{"cameraMode":{"drawMode":0,"name":"Shaded","section":"Shading Mode"},"sceneLighting":false,"audioPlay":false,"sceneViewState":{"showFog":true,"showMaterialUpdate":false,"showSkybox":false,"showFlares":true,"showImageEffects":true,"showParticleSystems":true},"in2DMode":false,"pivot":{"x":1.6230013370513917,"y":-0.37100720405578616,"z":-0.5650352835655212},"rotation":{"x":-0.15418432652950288,"y":-0.7272135019302368,"z":0.17360033094882966,"w":-0.6460354328155518},"size":5.974146842956543,"orthographic":false}